{
    "timestamp": "2025-05-09 23:06:58",
    "target_universities": [
        "四川大学",
        "电子科技大学",
        "西南交通大学",
        "西南财经大学",
        "四川师范大学",
        "成都理工大学",
        "西南科技大学",
        "成都信息工程大学",
        "西华大学",
        "成都大学"
    ],
    "target_major_codes": [
        "083500",
        "085400",
        "085410",
        "085405",
        "081200",
        "085411",
        "085404",
        "083900"
    ],
    "schools_processed": 3,
    "schools_updated": 1,
    "total_departments_found": 3,
    "total_majors_found": 11
}